db_operator/DBOperate.py
db_operator/__init__.py
db_operator_york-0.0.1.dist-info/LICENSE
db_operator_york-0.0.1.dist-info/METADATA
db_operator_york-0.0.1.dist-info/WHEEL
db_operator_york-0.0.1.dist-info/top_level.txt
db_operator_york-0.0.1.dist-info/RECORD
