Metadata-Version: 2.1
Name: db-operator-york
Version: 0.0.1
Summary: daas db operator
Home-page: https://github.com/pypa/sampleproject
Author: York Lei
Author-email: leity@smartsteps.com
Classifier: Programming Language :: Python :: 3
Classifier: License :: OSI Approved :: MIT License
Classifier: Operating System :: OS Independent
Requires-Python: >=3.0
License-File: LICENSE
Requires-Dist: pandas (>=1.3.5)
Requires-Dist: requests (>=2.28.1)
